odoo/addons/product_form_pricelist/README.rst
odoo/addons/product_form_pricelist/__init__.py
odoo/addons/product_form_pricelist/__manifest__.py
odoo/addons/product_form_pricelist/i18n/es.po
odoo/addons/product_form_pricelist/i18n/it.po
odoo/addons/product_form_pricelist/i18n/nl.po
odoo/addons/product_form_pricelist/i18n/product_form_pricelist.pot
odoo/addons/product_form_pricelist/models/__init__.py
odoo/addons/product_form_pricelist/models/product_pricelist_item.py
odoo/addons/product_form_pricelist/models/product_template.py
odoo/addons/product_form_pricelist/models/res_config_settings.py
odoo/addons/product_form_pricelist/readme/CONFIGURATION.rst
odoo/addons/product_form_pricelist/readme/CONTRIBUTORS.md
odoo/addons/product_form_pricelist/readme/DESCRIPTION.md
odoo/addons/product_form_pricelist/readme/USAGE.md
odoo/addons/product_form_pricelist/security/res_groups.xml
odoo/addons/product_form_pricelist/static/description/icon.png
odoo/addons/product_form_pricelist/static/description/index.html
odoo/addons/product_form_pricelist/tests/__init__.py
odoo/addons/product_form_pricelist/tests/test_pricelist.py
odoo/addons/product_form_pricelist/views/product_template_view.xml
odoo/addons/product_form_pricelist/views/product_view.xml
odoo/addons/product_form_pricelist/views/res_config_settings_view.xml
odoo_addon_product_form_pricelist-17.0.1.0.0.4.dist-info/METADATA
odoo_addon_product_form_pricelist-17.0.1.0.0.4.dist-info/WHEEL
odoo_addon_product_form_pricelist-17.0.1.0.0.4.dist-info/top_level.txt
odoo_addon_product_form_pricelist-17.0.1.0.0.4.dist-info/RECORD
